bootstrap.py
buildout.cfg
license.txt
setup.py
mortar/__init__.py
mortar/application.py
mortar/content.py
mortar/convertors.py
mortar/exceptions.py
mortar/field.py
mortar/interfaces.py
mortar/license.txt
mortar/search.py
mortar/server.py
mortar/storage.py
mortar/types.py
mortar/version.txt
mortar.egg-info/PKG-INFO
mortar.egg-info/SOURCES.txt
mortar.egg-info/dependency_links.txt
mortar.egg-info/not-zip-safe
mortar.egg-info/requires.txt
mortar.egg-info/top_level.txt
mortar/content/type.xml
mortar/docs/content.txt
mortar/docs/description.txt
mortar/storage/__init__.py
mortar/storage/directory.py
mortar/storage/tests/__init__.py
mortar/storage/tests/common.py
mortar/storage/tests/test_directory.py
mortar/storage/tests/data/directory/test.xml
mortar/tests/__init__.py
mortar/tests/common.py
mortar/tests/fixtures.py
mortar/tests/test_content.py
mortar/tests/test_convertors.py
mortar/tests/test_docs.py
mortar/tests/test_field.py
mortar/tests/test_field_types.py
mortar/tests/test_import.py