Metadata-Version: 1.0
Name: mortar
Version: 0.1.2
Summary: An implementation independent content environment.
Home-page: http://www.mortar.org
Author: Chris Withers
Author-email: chris@simplistix.co.uk
License: MIT
Platform: UNKNOWN
Classifier: Development Status :: 2 - Pre-Alpha
Classifier: Intended Audience :: Developers
Classifier: License :: OSI Approved :: MIT License
